LICENSE
MANIFEST.in
README.rst
requirements.txt
setup.py
docs/changelog.rst
mincss/__init__.py
mincss/__main__.py
mincss/download.js
mincss/main.py
mincss/processor.py
mincss3k.egg-info/PKG-INFO
mincss3k.egg-info/SOURCES.txt
mincss3k.egg-info/dependency_links.txt
mincss3k.egg-info/entry_points.txt
mincss3k.egg-info/not-zip-safe
mincss3k.egg-info/requires.txt
mincss3k.egg-info/top_level.txt
tests/__init__.py
tests/test_mincss.py